{
  "imp_indices": [
    4,
    5,
    6,
    7,
    9,
    14,
    662,
    663,
    664,
    665,
    666,
    667,
    668,
    669,
    670,
    671,
    672,
    673,
    674,
    675,
    676,
    677,
    678,
    679,
    680,
    681,
    682,
    683,
    684,
    685,
    686,
    687,
    688,
    689,
    690,
    691,
    692,
    693,
    694,
    695,
    696,
    697,
    698,
    699,
    700,
    701,
    702,
    703,
    704,
    705,
    706,
    707,
    708,
    709,
    710,
    711,
    712,
    713,
    715,
    716,
    717,
    718,
    719,
    720,
    721,
    722,
    723,
    724,
    725,
    726,
    727,
    728,
    729,
    730,
    731,
    732,
    733,
    734,
    738,
    740,
    741,
    743,
    744,
    745,
    746,
    747,
    748,
    749,
    750,
    751,
    753,
    756,
    758,
    759,
    760,
    761,
    762,
    763,
    764,
    765,
    766,
    767,
    771,
    773,
    774,
    775,
    776,
    777,
    778,
    783,
    784,
    785,
    786,
    787,
    788,
    789,
    792,
    796,
    798,
    799,
    800,
    801,
    802,
    803,
    804,
    805,
    806,
    807,
    812,
    813,
    814,
    815,
    816,
    819,
    820,
    821,
    828,
    833,
    834,
    838,
    839,
    841,
    847,
    849,
    861,
    870,
    872,
    876,
    877,
    878,
    879,
    895,
    907,
    1275,
    1277,
    1278,
    1279,
    1280,
    1281,
    1282,
    1283,
    1284,
    1285,
    1286,
    1287,
    1288,
    1289,
    1290,
    1291,
    1292,
    1293,
    1294,
    1295,
    1296,
    1297,
    1298,
    1299,
    1300,
    1301,
    1302,
    1303,
    1304,
    1305,
    1306,
    1307,
    1308,
    1309,
    1310,
    1311,
    1312,
    1313,
    1314,
    1315,
    1316,
    1317,
    1318,
    1319,
    1320,
    1321,
    1322,
    1323,
    1324,
    1325,
    1326,
    1327,
    1328,
    1330,
    1331,
    1332,
    1333,
    1334,
    1335,
    1336,
    1337,
    1338
  ],
  "ttft_with_cache": 0.02887248992919922,
  "output_text": " Wooden Crosses was made first. (based",
  "imp_indices_unsorted": [
    1278,
    663,
    662,
    1277,
    4,
    1279,
    664,
    1290,
    1313,
    1298,
    1309,
    1283,
    685,
    1305,
    667,
    1280,
    681,
    1284,
    675,
    1282,
    1291,
    1331,
    1288,
    1287,
    1293,
    686,
    1281,
    682,
    1303,
    1308,
    1310,
    1295,
    665,
    671,
    676,
    1297,
    672,
    696,
    1294,
    716,
    730,
    701,
    1311,
    1292,
    5,
    669,
    1286,
    758,
    1312,
    1301,
    1285,
    703,
    697,
    1306,
    1335,
    1299,
    1315,
    699,
    666,
    723,
    1302,
    1275,
    1334,
    783,
    1316,
    717,
    673,
    1304,
    691,
    1300,
    692,
    705,
    774,
    1330,
    759,
    677,
    693,
    683,
    812,
    709,
    713,
    668,
    694,
    741,
    6,
    674,
    802,
    1317,
    1314,
    799,
    706,
    1296,
    678,
    732,
    715,
    679,
    687,
    1289,
    702,
    690,
    1319,
    1307,
    775,
    839,
    704,
    748,
    1318,
    680,
    688,
    776,
    689,
    700,
    1320,
    698,
    725,
    684,
    800,
    724,
    720,
    738,
    670,
    764,
    1325,
    707,
    1321,
    801,
    746,
    1324,
    740,
    1336,
    708,
    734,
    751,
    731,
    767,
    1332,
    1333,
    784,
    787,
    745,
    834,
    778,
    719,
    1326,
    718,
    841,
    771,
    710,
    807,
    847,
    773,
    763,
    777,
    792,
    789,
    861,
    743,
    711,
    806,
    695,
    721,
    756,
    815,
    804,
    1323,
    838,
    816,
    726,
    733,
    849,
    879,
    9,
    727,
    805,
    7,
    729,
    798,
    814,
    788,
    1328,
    747,
    819,
    820,
    712,
    833,
    728,
    765,
    744,
    895,
    749,
    828,
    872,
    876,
    803,
    870,
    796,
    907,
    750,
    785,
    766,
    760,
    877,
    753,
    762,
    813,
    14,
    722,
    878,
    761,
    1337,
    1322,
    786,
    821,
    1327
  ],
  "imp_indices_last": [
    1338
  ]
}