{
  "imp_indices": [
    4,
    5,
    6,
    7,
    10,
    800,
    801,
    802,
    803,
    804,
    805,
    806,
    807,
    808,
    809,
    810,
    811,
    812,
    813,
    814,
    815,
    816,
    817,
    818,
    819,
    820,
    821,
    822,
    823,
    824,
    825,
    826,
    827,
    828,
    829,
    830,
    831,
    832,
    833,
    834,
    835,
    836,
    837,
    839,
    840,
    841,
    842,
    843,
    844,
    845,
    846,
    847,
    848,
    849,
    850,
    851,
    852,
    853,
    854,
    855,
    856,
    857,
    859,
    860,
    861,
    862,
    863,
    864,
    865,
    866,
    867,
    868,
    869,
    870,
    871,
    872,
    873,
    874,
    875,
    876,
    878,
    879,
    880,
    881,
    882,
    883,
    884,
    885,
    886,
    887,
    888,
    889,
    890,
    891,
    892,
    893,
    894,
    895,
    896,
    897,
    898,
    899,
    900,
    901,
    902,
    903,
    904,
    905,
    906,
    907,
    908,
    909,
    910,
    911,
    912,
    913,
    914,
    915,
    916,
    919,
    922,
    923,
    924,
    925,
    926,
    927,
    929,
    930,
    931,
    932,
    934,
    935,
    936,
    939,
    940,
    941,
    942,
    944,
    945,
    947,
    949,
    950,
    951,
    953,
    955,
    956,
    959,
    964,
    966,
    968,
    970,
    971,
    972,
    975,
    978,
    979,
    982,
    983,
    984,
    986,
    987,
    989,
    993,
    997,
    998,
    999,
    1001,
    1003,
    1007,
    1012,
    1017,
    1018,
    1022,
    1025,
    1026,
    1032,
    1038,
    1043,
    1056,
    1062,
    1070,
    1086,
    1107,
    1108,
    1140,
    1147,
    1165,
    1210,
    1527,
    1528,
    1529,
    1530,
    1531,
    1532,
    1533,
    1534,
    1535,
    1536,
    1537,
    1538,
    1539,
    1540,
    1541,
    1542,
    1543,
    1544,
    1545,
    1546,
    1547,
    1548,
    1549,
    1550,
    1551,
    1552,
    1553,
    1554,
    1555,
    1556,
    1557,
    1558,
    1559,
    1560,
    1561,
    1562,
    1563,
    1564,
    1565,
    1566,
    1567,
    1568,
    1569,
    1570,
    1571,
    1572,
    1573,
    1574,
    1575,
    1576,
    1577,
    1578,
    1579,
    1580,
    1581,
    1582,
    1583,
    1584,
    1585,
    1586,
    1587,
    1588,
    1589,
    1590,
    1591,
    1592,
    1593
  ],
  "ttft_with_cache": 0.030521154403686523,
  "output_text": " Arthur Acheson, 1st Earl of",
  "imp_indices_unsorted": [
    1528,
    801,
    1527,
    800,
    4,
    1529,
    802,
    1540,
    1534,
    1559,
    1548,
    1555,
    803,
    1533,
    1538,
    1530,
    1541,
    804,
    1532,
    805,
    1558,
    1537,
    1586,
    1547,
    817,
    1531,
    1544,
    1562,
    824,
    1543,
    1560,
    1551,
    1542,
    1545,
    1561,
    1574,
    1590,
    1549,
    1556,
    1579,
    1536,
    1553,
    1535,
    1554,
    1563,
    1585,
    807,
    1550,
    811,
    823,
    1552,
    1571,
    1570,
    1564,
    818,
    812,
    831,
    808,
    5,
    825,
    1589,
    826,
    1581,
    864,
    1573,
    1575,
    829,
    1546,
    816,
    1584,
    815,
    1567,
    813,
    822,
    832,
    814,
    847,
    836,
    1557,
    821,
    1539,
    806,
    1576,
    833,
    908,
    820,
    819,
    845,
    828,
    6,
    827,
    1572,
    940,
    853,
    856,
    1591,
    854,
    809,
    839,
    1565,
    982,
    863,
    841,
    1587,
    840,
    844,
    971,
    851,
    1588,
    830,
    846,
    848,
    1017,
    878,
    849,
    1580,
    885,
    843,
    865,
    850,
    897,
    867,
    905,
    866,
    1568,
    1583,
    1107,
    922,
    929,
    810,
    910,
    874,
    898,
    916,
    1566,
    879,
    935,
    947,
    883,
    979,
    859,
    862,
    919,
    869,
    875,
    881,
    1577,
    1582,
    1592,
    904,
    868,
    939,
    872,
    909,
    978,
    1062,
    852,
    870,
    913,
    951,
    959,
    903,
    889,
    842,
    1001,
    896,
    936,
    1569,
    892,
    950,
    860,
    882,
    927,
    989,
    888,
    925,
    871,
    970,
    880,
    886,
    907,
    915,
    1210,
    884,
    902,
    1038,
    834,
    893,
    899,
    911,
    900,
    1026,
    1578,
    891,
    837,
    887,
    901,
    941,
    934,
    890,
    895,
    7,
    926,
    975,
    906,
    912,
    986,
    987,
    894,
    972,
    955,
    993,
    1056,
    923,
    1012,
    873,
    983,
    1140,
    1147,
    997,
    857,
    932,
    998,
    968,
    942,
    999,
    956,
    861,
    876,
    953,
    1165,
    930,
    944,
    1032,
    1070,
    10,
    835,
    931,
    1003,
    1043,
    1086,
    855,
    914,
    1018,
    924,
    964,
    945,
    1007,
    949,
    1022,
    1108,
    984,
    966,
    1025
  ],
  "imp_indices_last": [
    1593
  ]
}